{
  "minecraft:recipe_shaped": {
    "description": {
      "identifier": "dw623:brick.jungle.slab.combo_recipe1"
    },
    "pattern": [
      "111",
      "ggg",
      "222"
    ],
    "tags": [
      "crafting_table"
    ],
    "key": {
      "1": {
        "item": "minecraft:brick_slab"
      },
      "g": {
        "item": "dw623:slime_glue_sheet"
      },
      "2": {
        "item": "minecraft:jungle_slab"
      }
    },
    "unlock": [
      {
        "item": "minecraft:brick_slab"
      },
      {
        "item": "minecraft:jungle_slab"
      }
    ],
    "result": {
      "item": "dw623:brick.jungle.slab.combo",
      "count": 3
    }
  },
  "format_version": "1.20.10"
}