{
  "minecraft:recipe_shaped": {
    "description": {
      "identifier": "dw623:exposed_c3tc6r.sandstone.slab.combo_recipe2"
    },
    "pattern": [
      "222",
      "ggg",
      "111"
    ],
    "tags": [
      "crafting_table"
    ],
    "key": {
      "1": {
        "item": "minecraft:exposed_cut_copper_slab"
      },
      "g": {
        "item": "dw623:slime_glue_sheet"
      },
      "2": {
        "item": "minecraft:sandstone_slab"
      }
    },
    "unlock": [
      {
        "item": "minecraft:exposed_cut_copper_slab"
      },
      {
        "item": "minecraft:sandstone_slab"
      }
    ],
    "result": {
      "item": "dw623:exposed_cut_copper.sandstone.slab.combo",
      "count": 3
    }
  },
  "format_version": "1.20.10"
}